{"pid":161,"slug":"beautiful-pairs","inferred_constraints":"2 <= nums1.length == nums2.length <= 1e5, 0 <= nums1[i] <= nums1.length, 0 <= nums2[i] <= nums2.length","input_format":"line1: nums1 (JSON int array); line2: nums2 (JSON int array)","testcases":[{"input":"[-1000]\n[-1000]","desc":"Edge: n=1 or minimal input","output":"[-1, -1]"},{"input":"[1,2,4,3,2,5]\n[1,4,2,3,5,1]","desc":"Edge: example2","output":"[1, 4]"},{"input":"[0,0]\n[0,0]","desc":"Edge: n=2 min length all zeros","output":"[0, 1]"},{"input":"[1,1]\n[1,1]","desc":"Edge: n=2 same points","output":"[0, 1]"},{"input":"[1,2]\n[1,2]","desc":"Edge: n=2 distinct points","output":"[0, 1]"},{"input":"[2,2,2]\n[2,2,2]","desc":"Edge: n=3 all same","output":"[0, 1]"},{"input":"[-588,308,-567,-384,-42,553,-739,-288,-855,395,581,-165,-822]\n[837,-301,-456,-340,715,909,545,796,937,-665,801,656,-553]","desc":"Regenerated: diverse at position 6","output":"[5, 10]"},{"input":"[-591,585,477,-297,5,-647,422,674,-605,-728,555,-591,-46,723,-676,-830,-771,-290,-457,-304,-719,934,188,-112,183,733,730,560,-730,818,-615,-374,-18,949,706,-908,506,-679,-371,-496,360,746,-672,452,-670,-931,-484,324,-751,-294,906,-801,47,515,710,11,795,887,-949,161,778,-202,-925,-383,803,-505,944,830,671,-273,106,-206,-72,693,-148,-695,-952,-780,-153,683,937,259,200,-817]\n[34,975,282,57,968,471,-819,-169,-493,-843,770,-429,894,661,-744,902,-512,-97,68,906,641,209,-265,587,-862,221,10,919,-809,367,245,-563,847,26,293,281,-889,571,-135,943,445,578,763,-725,-112,-428,-469,909,323,509,-715,-460,-602,-391,624,245,578,-673,-146,248,1000,595,316,686,509,-147,921,257,653,261,891,60,246,910,-685,-79,494,-23,527,-63,846,-729,651,-665]","desc":"Regenerated: diverse at position 7","output":"[9, 28]"},{"input":"[5,5,5,5,5]\n[5,5,5,5,5]","desc":"Edge: all identical points","output":"[0, 1]"},{"input":"[1,3,5,7]\n[2,4,6,8]","desc":"Standard: ascending points","output":"[0, 1]"},{"input":"[8,6,4,2]\n[7,5,3,1]","desc":"Standard: descending","output":"[0, 1]"},{"input":"[1,2,1,2,1]\n[2,1,2,1,2]","desc":"Standard: alternating","output":"[0, 2]"},{"input":"[1,2,3,4,5,6]\n[6,5,4,3,2,1]","desc":"Standard: opposite slopes","output":"[0, 1]"},{"input":"[3,1,4,1,5,9,2,6]\n[5,3,5,8,9,7,9,3]","desc":"Standard: pi","output":"[0, 2]"},{"input":"[10,9,8,7,6,5,4,3,2,1]\n[1,2,3,4,5,6,7,8,9,10]","desc":"Standard: opposing orders","output":"[0, 1]"},{"input":"[0,1,0,1,0]\n[1,0,1,0,1]","desc":"Standard: binary alternation","output":"[0, 2]"},{"input":"[2,3,2,3]\n[2,3,3,2]","desc":"Standard: small mix","output":"[0, 2]"},{"input":"[1,2,3,4,5,6,7,8,9,10,1,2,3,4,5,6,7,8,9,10]\n[10,9,8,7,6,5,4,3,2,1,1,2,3,4,5,6,7,8,9,10]","desc":"Stress: 20 points","output":"[4, 14]"},{"input":"[5,4,3,2,1,5,4,3,2,1,5,4,3,2,1]\n[1,2,3,4,5,1,2,3,4,5,1,2,3,4,5]","desc":"Stress: 15 repeating patterns","output":"[0, 5]"},{"input":"[0,1,2,3,4,5,6,7,8,9,10,11,12,13,14,15,16,17,18,19]\n[19,18,17,16,15,14,13,12,11,10,9,8,7,6,5,4,3,2,1,0]","desc":"Stress: 20 ascending vs descending","output":"[0, 1]"}]}