{
  "pid": 1969,
  "slug": "strictly-palindromic-number",
  "inferred_constraints": "4 <= n <= 10^5",
  "input_format": "single line: n (int)",
  "testcases": [
    {
      "input": "4",
      "desc": "Edge: n=1 or minimal input",
      "output": "false"
    },
    {
      "input": "4",
      "desc": "Standard: example 2 minimum",
      "output": "false"
    },
    {
      "input": "5",
      "desc": "Edge: smallest",
      "output": "false"
    },
    {
      "input": "6",
      "desc": "Edge",
      "output": "false"
    },
    {
      "input": "7",
      "desc": "Edge",
      "output": "false"
    },
    {
      "input": "8",
      "desc": "Edge",
      "output": "false"
    },
    {
      "input": "10",
      "desc": "Standard",
      "output": "false"
    },
    {
      "input": "100",
      "desc": "Standard: medium",
      "output": "false"
    },
    {
      "input": "1000",
      "desc": "Standard",
      "output": "false"
    },
    {
      "input": "10000",
      "desc": "Standard: large",
      "output": "false"
    },
    {
      "input": "100000",
      "desc": "Edge: max",
      "output": "false"
    },
    {
      "input": "50",
      "desc": "Standard",
      "output": "false"
    },
    {
      "input": "99",
      "desc": "Standard: just under 100",
      "output": "false"
    },
    {
      "input": "999",
      "desc": "Standard",
      "output": "false"
    },
    {
      "input": "99999",
      "desc": "Standard: near max",
      "output": "false"
    },
    {
      "input": "12",
      "desc": "Standard",
      "output": "false"
    },
    {
      "input": "16",
      "desc": "Standard: power of 2",
      "output": "false"
    },
    {
      "input": "27",
      "desc": "Standard: power of 3",
      "output": "false"
    },
    {
      "input": "256",
      "desc": "Standard: power",
      "output": "false"
    },
    {
      "input": "65536",
      "desc": "Standard: 2^16",
      "output": "false"
    }
  ]
}