{"pid":252,"slug":"take-k-of-each-character-from-left-and-right","inferred_constraints":"1 <= s.length <= 1e5, s in 'abc', 0 <= k <= s.length","input_format":"line1: s (string in JSON quotes); line2: k (int)","testcases":[{"input":"\"k\"\n0","desc":"Edge: n=1 or minimal input","output":"0"},{"input":"\"a\"\n1","desc":"Edge: example2 -1","output":"-1"},{"input":"\"urapyaoqomsq\"\n2","desc":"Edge: monotone increasing sequence","output":"-1"},{"input":"\"pgjxsa\"\n1","desc":"Edge: monotone decreasing sequence","output":"-1"},{"input":"\"rzckbvnr\"\n0","desc":"Edge: all-equal elements","output":"0"},{"input":"\"aaa\"\n1","desc":"Edge: no b/c -> -1","output":"-1"},{"input":"\"bbb\"\n1","desc":"Edge: no a/c -> -1","output":"-1"},{"input":"\"ccc\"\n1","desc":"Edge: no a/b -> -1","output":"-1"},{"input":"\"abcabc\"\n2","desc":"Edge: 2 of each","output":"6"},{"input":"\"aaaabbbbcccc\"\n4","desc":"Edge: clusters","output":"12"},{"input":"\"abcabcabcabc\"\n4","desc":"Standard: repeating cycles","output":"12"},{"input":"\"aaabbbccc\"\n3","desc":"Standard: clean clusters","output":"9"},{"input":"\"cccbbbaaa\"\n3","desc":"Standard: reverse clusters","output":"9"},{"input":"\"abccba\"\n2","desc":"Standard: palindrome small","output":"6"},{"input":"\"cabacb\"\n2","desc":"Standard: mixed","output":"6"},{"input":"\"aaaaaabbbbbbcccccc\"\n5","desc":"Standard: 6 each","output":"16"},{"input":"\"abcabcabcabcabcabcabc\"\n7","desc":"Standard: 7 cycles","output":"21"},{"input":"\"abcabcabcabcabcabcabcabcabcabcabcabcabcabcabcabcabcabcabcabcabcabcabcabcabcabcabcabcabcabcabcabcabcabc\"\n30","desc":"Stress: 33 cycles, k=30","output":"90"},{"input":"\"aaaaaaaaaabbbbbbbbbbcccccccccc\"\n10","desc":"Stress: 10+10+10","output":"30"},{"input":"\"sarijeyrjmzfqoksrbmpmroa\"\n2","desc":"Stress: large n near max boundary","output":"-1"}]}