{"pid":414,"slug":"count-the-number-of-winning-sequences","inferred_constraints":"1 <= n == s.length <= 1000, s in {'F','W','E'}","input_format":"line1: s (raw string)","testcases":[{"input":"F","desc":"Edge: n=1 single F","output":"1"},{"input":"W","desc":"Edge: n=1 single W","output":"1"},{"input":"\"pf\"","desc":"Edge: monotone increasing sequence","output":""},{"input":"\"od\"","desc":"Edge: monotone decreasing sequence","output":""},{"input":"\"m\"","desc":"Edge: all-equal elements","output":""},{"input":"EF","desc":"Edge: n=2 EF","output":"2"},{"input":"FF","desc":"Edge: n=2 same","output":"2"},{"input":"FWE","desc":"Standard: n=3 all distinct","output":"4"},{"input":"FFF","desc":"Edge: all F","output":"3"},{"input":"WWWWWWWWWW","desc":"Edge: n=10 all W","output":"574"},{"input":"EEEEEEEEEE","desc":"Edge: n=10 all E","output":"574"},{"input":"FWEFWE","desc":"Standard: pattern","output":"38"},{"input":"FFFFFWWWWW","desc":"Standard: blocks","output":"588"},{"input":"FWEWFE","desc":"Standard: mixed","output":"38"},{"input":"FFFEEEFFFEEE","desc":"Standard: F E blocks alternating","output":"2485"},{"input":"WWEEFFWWEEFFWWEEFF","desc":"Standard: pairs cycling","output":"166781"},{"input":"FWEFWEFWEFWEFWEFWEFWEFWEFWEFWEFWEFWEFWEFWEFWEFWEFWE","desc":"Stress: n=51 FWE pattern","output":"536113907"},{"input":"FFFFFFFFFFFFFFFFFFFFFFFFFFFFFF","desc":"Stress: 30 F","output":"683845476"},{"input":"WFEWFEWFEWFEWFEWFEWFEWFEWFEWFE","desc":"Stress: WFE pattern","output":"732835478"},{"input":"\"oujz\"","desc":"Stress: large n near max boundary","output":""}]}