{"pid":837,"slug":"divide-two-integers","inferred_constraints":"-2^31 <= dividend, divisor <= 2^31-1, divisor != 0","input_format":"line1: dividend (int); line2: divisor (int)","testcases":[{"input":"0\n-3","desc":"Edge: n=1 or minimal input","output":"0"},{"input":"7\n-3","desc":"Edge: example2","output":"-2"},{"input":"3\n0","desc":"Edge: monotone increasing sequence","output":""},{"input":"6\n1","desc":"Edge: monotone decreasing sequence","output":"6"},{"input":"3\n0","desc":"Edge: all-equal elements","output":""},{"input":"-1\n1","desc":"Edge: -1 / 1","output":"-1"},{"input":"1\n-1","desc":"Edge: 1 / -1","output":"-1"},{"input":"-1\n-1","desc":"Edge: -1 / -1","output":"1"},{"input":"2147483647\n1","desc":"Edge: INT_MAX","output":"2147483647"},{"input":"-2147483648\n1","desc":"Edge: INT_MIN","output":"-2147483648"},{"input":"-2147483648\n-1","desc":"Edge: overflow case","output":"2147483647"},{"input":"2147483647\n2147483647","desc":"Edge: max/max","output":"1"},{"input":"100\n10","desc":"Standard: 100/10","output":"10"},{"input":"100\n-10","desc":"Standard: 100/-10","output":"-10"},{"input":"-100\n10","desc":"Standard: -100/10","output":"-10"},{"input":"-100\n-10","desc":"Standard: -100/-10","output":"10"},{"input":"1024\n2","desc":"Standard: 1024/2","output":"512"},{"input":"1000000000\n3","desc":"Standard: 1e9/3","output":"333333333"},{"input":"-2147483648\n2","desc":"Edge: INT_MIN/2","output":"-1073741824"},{"input":"7\n2","desc":"Special: 7/2","output":"3"}]}