{
  "questionId": "714",
  "questionFrontendId": "714",
  "title": "Best Time to Buy and Sell Stock with Transaction Fee",
  "titleSlug": "best-time-to-buy-and-sell-stock-with-transaction-fee",
  "content": "<p>You are given an array <code>prices</code> where <code>prices[i]</code> is the price of a given stock on the <code>i<sup>th</sup></code> day, and an integer <code>fee</code> representing a transaction fee.</p>\n\n<p>Find the maximum profit you can achieve. You may complete as many transactions as you like, but you need to pay the transaction fee for each transaction.</p>\n\n<p><strong>Note:</strong></p>\n\n<ul>\n\t<li>You may not engage in multiple transactions simultaneously (i.e., you must sell the stock before you buy again).</li>\n\t<li>The transaction fee is only charged once for each stock purchase and sale.</li>\n</ul>\n\n<p>&nbsp;</p>\n<p><strong class=\"example\">Example 1:</strong></p>\n\n<pre>\n<strong>Input:</strong> prices = [1,3,2,8,4,9], fee = 2\n<strong>Output:</strong> 8\n<strong>Explanation:</strong> The maximum profit can be achieved by:\n- Buying at prices[0] = 1\n- Selling at prices[3] = 8\n- Buying at prices[4] = 4\n- Selling at prices[5] = 9\nThe total profit is ((8 - 1) - 2) + ((9 - 4) - 2) = 8.\n</pre>\n\n<p><strong class=\"example\">Example 2:</strong></p>\n\n<pre>\n<strong>Input:</strong> prices = [1,3,7,5,10,3], fee = 3\n<strong>Output:</strong> 6\n</pre>\n\n<p>&nbsp;</p>\n<p><strong>Constraints:</strong></p>\n\n<ul>\n\t<li><code>1 &lt;= prices.length &lt;= 5 * 10<sup>4</sup></code></li>\n\t<li><code>1 &lt;= prices[i] &lt; 5 * 10<sup>4</sup></code></li>\n\t<li><code>0 &lt;= fee &lt; 5 * 10<sup>4</sup></code></li>\n</ul>\n",
  "difficulty": "Medium",
  "codeSnippets": [
    {
      "lang": "C++",
      "code": "class Solution {\npublic:\n    int maxProfit(vector<int>& prices, int fee) {\n        \n    }\n};"
    },
    {
      "lang": "Java",
      "code": "class Solution {\n    public int maxProfit(int[] prices, int fee) {\n        \n    }\n}"
    },
    {
      "lang": "Python3",
      "code": "class Solution:\n    def maxProfit(self, prices: List[int], fee: int) -> int:\n        "
    },
    {
      "lang": "Python",
      "code": "class Solution(object):\n    def maxProfit(self, prices, fee):\n        \"\"\"\n        :type prices: List[int]\n        :type fee: int\n        :rtype: int\n        \"\"\"\n        "
    },
    {
      "lang": "JavaScript",
      "code": "/**\n * @param {number[]} prices\n * @param {number} fee\n * @return {number}\n */\nvar maxProfit = function(prices, fee) {\n    \n};"
    },
    {
      "lang": "TypeScript",
      "code": "function maxProfit(prices: number[], fee: number): number {\n    \n};"
    },
    {
      "lang": "C#",
      "code": "public class Solution {\n    public int MaxProfit(int[] prices, int fee) {\n        \n    }\n}"
    },
    {
      "lang": "C",
      "code": "int maxProfit(int* prices, int pricesSize, int fee) {\n    \n}"
    },
    {
      "lang": "Go",
      "code": "func maxProfit(prices []int, fee int) int {\n    \n}"
    },
    {
      "lang": "Kotlin",
      "code": "class Solution {\n    fun maxProfit(prices: IntArray, fee: Int): Int {\n        \n    }\n}"
    },
    {
      "lang": "Swift",
      "code": "class Solution {\n    func maxProfit(_ prices: [Int], _ fee: Int) -> Int {\n        \n    }\n}"
    },
    {
      "lang": "Rust",
      "code": "impl Solution {\n    pub fn max_profit(prices: Vec<i32>, fee: i32) -> i32 {\n        \n    }\n}"
    },
    {
      "lang": "Ruby",
      "code": "# @param {Integer[]} prices\n# @param {Integer} fee\n# @return {Integer}\ndef max_profit(prices, fee)\n    \nend"
    },
    {
      "lang": "PHP",
      "code": "class Solution {\n\n    /**\n     * @param Integer[] $prices\n     * @param Integer $fee\n     * @return Integer\n     */\n    function maxProfit($prices, $fee) {\n        \n    }\n}"
    },
    {
      "lang": "Dart",
      "code": "class Solution {\n  int maxProfit(List<int> prices, int fee) {\n    \n  }\n}"
    },
    {
      "lang": "Scala",
      "code": "object Solution {\n    def maxProfit(prices: Array[Int], fee: Int): Int = {\n        \n    }\n}"
    },
    {
      "lang": "Elixir",
      "code": "defmodule Solution do\n  @spec max_profit(prices :: [integer], fee :: integer) :: integer\n  def max_profit(prices, fee) do\n    \n  end\nend"
    },
    {
      "lang": "Erlang",
      "code": "-spec max_profit(Prices :: [integer()], Fee :: integer()) -> integer().\nmax_profit(Prices, Fee) ->\n  ."
    },
    {
      "lang": "Racket",
      "code": "(define/contract (max-profit prices fee)\n  (-> (listof exact-integer?) exact-integer? exact-integer?)\n  )"
    }
  ],
  "stats": "{\"totalAccepted\": \"557.9K\", \"totalSubmission\": \"778.4K\", \"totalAcceptedRaw\": 557857, \"totalSubmissionRaw\": 778368, \"acRate\": \"71.7%\"}",
  "metaData": "{\r\n  \"name\": \"maxProfit\",\r\n  \"params\": [\r\n    {\r\n      \"name\": \"prices\",\r\n      \"type\": \"integer[]\"\r\n    },\r\n    {\r\n      \"name\": \"fee\",\r\n      \"type\": \"integer\"\r\n    }\r\n  ],\r\n  \"return\": {\r\n    \"type\": \"integer\"\r\n  }\r\n}\r\n",
  "sampleTestCase": "[1,3,2,8,4,9]\n2"
}