{
  "questionId": "525",
  "questionFrontendId": "525",
  "title": "Contiguous Array",
  "titleSlug": "contiguous-array",
  "content": "<p>Given a binary array <code>nums</code>, return <em>the maximum length of a contiguous subarray with an equal number of </em><code>0</code><em> and </em><code>1</code>.</p>\n\n<p>&nbsp;</p>\n<p><strong class=\"example\">Example 1:</strong></p>\n\n<pre>\n<strong>Input:</strong> nums = [0,1]\n<strong>Output:</strong> 2\n<strong>Explanation:</strong> [0, 1] is the longest contiguous subarray with an equal number of 0 and 1.\n</pre>\n\n<p><strong class=\"example\">Example 2:</strong></p>\n\n<pre>\n<strong>Input:</strong> nums = [0,1,0]\n<strong>Output:</strong> 2\n<strong>Explanation:</strong> [0, 1] (or [1, 0]) is a longest contiguous subarray with equal number of 0 and 1.\n</pre>\n\n<p><strong class=\"example\">Example 3:</strong></p>\n\n<pre>\n<strong>Input:</strong> nums = [0,1,1,1,1,1,0,0,0]\n<strong>Output:</strong> 6\n<strong>Explanation:</strong> [1,1,1,0,0,0] is the longest contiguous subarray with equal number of 0 and 1.\n</pre>\n\n<p>&nbsp;</p>\n<p><strong>Constraints:</strong></p>\n\n<ul>\n\t<li><code>1 &lt;= nums.length &lt;= 10<sup>5</sup></code></li>\n\t<li><code>nums[i]</code> is either <code>0</code> or <code>1</code>.</li>\n</ul>\n",
  "difficulty": "Medium",
  "codeSnippets": [
    {
      "lang": "C++",
      "code": "class Solution {\npublic:\n    int findMaxLength(vector<int>& nums) {\n        \n    }\n};"
    },
    {
      "lang": "Java",
      "code": "class Solution {\n    public int findMaxLength(int[] nums) {\n        \n    }\n}"
    },
    {
      "lang": "Python3",
      "code": "class Solution:\n    def findMaxLength(self, nums: List[int]) -> int:\n        "
    },
    {
      "lang": "Python",
      "code": "class Solution(object):\n    def findMaxLength(self, nums):\n        \"\"\"\n        :type nums: List[int]\n        :rtype: int\n        \"\"\"\n        "
    },
    {
      "lang": "JavaScript",
      "code": "/**\n * @param {number[]} nums\n * @return {number}\n */\nvar findMaxLength = function(nums) {\n    \n};"
    },
    {
      "lang": "TypeScript",
      "code": "function findMaxLength(nums: number[]): number {\n    \n};"
    },
    {
      "lang": "C#",
      "code": "public class Solution {\n    public int FindMaxLength(int[] nums) {\n        \n    }\n}"
    },
    {
      "lang": "C",
      "code": "int findMaxLength(int* nums, int numsSize) {\n    \n}"
    },
    {
      "lang": "Go",
      "code": "func findMaxLength(nums []int) int {\n    \n}"
    },
    {
      "lang": "Kotlin",
      "code": "class Solution {\n    fun findMaxLength(nums: IntArray): Int {\n        \n    }\n}"
    },
    {
      "lang": "Swift",
      "code": "class Solution {\n    func findMaxLength(_ nums: [Int]) -> Int {\n        \n    }\n}"
    },
    {
      "lang": "Rust",
      "code": "impl Solution {\n    pub fn find_max_length(nums: Vec<i32>) -> i32 {\n        \n    }\n}"
    },
    {
      "lang": "Ruby",
      "code": "# @param {Integer[]} nums\n# @return {Integer}\ndef find_max_length(nums)\n    \nend"
    },
    {
      "lang": "PHP",
      "code": "class Solution {\n\n    /**\n     * @param Integer[] $nums\n     * @return Integer\n     */\n    function findMaxLength($nums) {\n        \n    }\n}"
    },
    {
      "lang": "Dart",
      "code": "class Solution {\n  int findMaxLength(List<int> nums) {\n    \n  }\n}"
    },
    {
      "lang": "Scala",
      "code": "object Solution {\n    def findMaxLength(nums: Array[Int]): Int = {\n        \n    }\n}"
    },
    {
      "lang": "Elixir",
      "code": "defmodule Solution do\n  @spec find_max_length(nums :: [integer]) :: integer\n  def find_max_length(nums) do\n    \n  end\nend"
    },
    {
      "lang": "Erlang",
      "code": "-spec find_max_length(Nums :: [integer()]) -> integer().\nfind_max_length(Nums) ->\n  ."
    },
    {
      "lang": "Racket",
      "code": "(define/contract (find-max-length nums)\n  (-> (listof exact-integer?) exact-integer?)\n  )"
    }
  ],
  "stats": "{\"totalAccepted\": \"645.3K\", \"totalSubmission\": \"1.3M\", \"totalAcceptedRaw\": 645343, \"totalSubmissionRaw\": 1272133, \"acRate\": \"50.7%\"}",
  "metaData": "{\r\n  \"name\": \"findMaxLength\",\r\n  \"params\": [\r\n    {\r\n      \"name\": \"nums\",\r\n      \"type\": \"integer[]\"\r\n    }\r\n  ],\r\n  \"return\": {\r\n    \"type\": \"integer\"\r\n  }\r\n}\r\n",
  "sampleTestCase": "[0,1]"
}